[
  {
    "inputs": [
      {
        "internalType": "address",
        "name": "_triageGroup",
        "type": "address"
      },
      {
        "internalType": "address",
        "name": "_manager",
        "type": "address"
      }
    ],
    "stateMutability": "nonpayable",
    "type": "constructor"
  },
  {
    "inputs": [
      {
        "internalType": "address",
        "name": "_grant",
        "type": "address"
      }
    ],
    "name": "allowGrant",
    "outputs": [],
    "stateMutability": "nonpayable",
    "type": "function"
  },
  {
    "inputs": [
      {
        "internalType": "address",
        "name": "",
        "type": "address"
      }
    ],
    "name": "allowed",
    "outputs": [
      {
        "internalType": "bool",
        "name": "",
        "type": "bool"
      }
    ],
    "stateMutability": "view",
    "type": "function"
  },
  {
    "inputs": [
      {
        "internalType": "uint256",
        "name": "currentReputationPoint",
        "type": "uint256"
      },
      {
        "internalType": "bool",
        "name": "isAligned",
        "type": "bool"
      }
    ],
    "name": "calculateReputationPoints",
    "outputs": [
      {
        "internalType": "uint256",
        "name": "",
        "type": "uint256"
      }
    ],
    "stateMutability": "pure",
    "type": "function"
  },
  {
    "inputs": [
      {
        "internalType": "address",
        "name": "_curator",
        "type": "address"
      }
    ],
    "name": "getCurationWeight",
    "outputs": [
      {
        "internalType": "uint256",
        "name": "",
        "type": "uint256"
      }
    ],
    "stateMutability": "view",
    "type": "function"
  },
  {
    "inputs": [
      {
        "internalType": "address",
        "name": "_curator",
        "type": "address"
      }
    ],
    "name": "getReputationPoint",
    "outputs": [
      {
        "internalType": "uint256",
        "name": "",
        "type": "uint256"
      }
    ],
    "stateMutability": "view",
    "type": "function"
  },
  {
    "inputs": [
      {
        "internalType": "address",
        "name": "",
        "type": "address"
      }
    ],
    "name": "reputations",
    "outputs": [
      {
        "internalType": "uint256",
        "name": "",
        "type": "uint256"
      }
    ],
    "stateMutability": "view",
    "type": "function"
  },
  {
    "inputs": [
      {
        "internalType": "address",
        "name": "_curator",
        "type": "address"
      },
      {
        "internalType": "bool",
        "name": "_isAligned",
        "type": "bool"
      }
    ],
    "name": "setReputations",
    "outputs": [],
    "stateMutability": "nonpayable",
    "type": "function"
  }
]
